README.rst
setup.py
scikit_spectra.egg-info/PKG-INFO
scikit_spectra.egg-info/SOURCES.txt
scikit_spectra.egg-info/dependency_links.txt
scikit_spectra.egg-info/entry_points.txt
scikit_spectra.egg-info/top_level.txt
skspec/__init__.py
skspec/config.py
skspec/exceptions.py
skspec/logger.py
skspec/IO/__init__.py
skspec/IO/csv_wrapper.py
skspec/IO/gwu_interfaces.py
skspec/IO/specrecord.py
skspec/bundled/__init__.py
skspec/bundled/gwu.css
skspec/bundled/nbstyles.py
skspec/bundled/nbutils.py
skspec/chaco_interface/__init__.py
skspec/chaco_interface/pandasplotdata.py
skspec/chaco_interface/pandasplotdatav2.py
skspec/chaco_interface/pandasplotdatav3.py
skspec/chaco_interface/pandasplots.py
skspec/chaco_interface/pandasplotsv2.py
skspec/chaco_interface/spectral_converter_demo.py
skspec/chaco_interface/spectralplotdata.py
skspec/core/__init__.py
skspec/core/abcindex.py
skspec/core/abcspectra.py
skspec/core/anyspectra.py
skspec/core/baseline.py
skspec/core/file_utils.py
skspec/core/specindex.py
skspec/core/specpanel.py
skspec/core/specstack.py
skspec/core/spectra.py
skspec/core/tempspectra.py
skspec/core/timeindex.py
skspec/core/timespectra.py
skspec/core/utilities.py
skspec/correlation/__init__.py
skspec/correlation/corr.py
skspec/correlation/pca_lite.py
skspec/correlation/pcakernel.py
skspec/data/__init__.py
skspec/data/__init__.pyc
skspec/data/_script_nb.ipynb
skspec/data/aunps_glass_bad.csv
skspec/data/aunps_glass_fair.csv
skspec/data/aunps_glass_full.csv
skspec/data/aunps_glass_good.csv
skspec/data/aunps_water.csv
skspec/data/coverimage.png
skspec/data/gwu.png
skspec/data/pskdt.csv
skspec/data/quaroni.dpt
skspec/data/triple_peaks.csv
skspec/interact/__init__.py
skspec/interact/ipynbs/__init__.py
skspec/interact/ipynbs/line_plugin.py
skspec/interact/ipynbs/nbtools.py
skspec/interact/ipynbs/specgram.py
skspec/interact/ipynbs/specgui.py
skspec/interact/ipynbs/corrgui/Corrspecgram.py
skspec/interact/ipynbs/corrgui/Corrspecgui.py
skspec/interact/ipynbs/corrgui/__init__.py
skspec/interact/ipynbs/corrgui/specgram.py
skspec/interact/ipynbs/corrgui/specgram_old.py
skspec/interact/ipynbs/corrgui/specgui.py
skspec/interact/ipynbs/corrgui/specgui_old.py
