Metadata-Version: 1.1
Name: scikit-spectra
Version: 0.3.2.2
Summary: Spectroscopy in Python built on Pandas.
Home-page: http://hugadams.github.io/scikit-spectra/
Author: Adam Hughes
Author-email: hughesadam87@gmail.com
License: LICENSE.txt
Download-URL: https://github.com/hugadams/scikit-spectra
Platform: UNKNOWN
Classifier: Development Status :: 3 - Alpha
Classifier: Environment :: Console
Classifier: Intended Audience :: Science/Research
Classifier: Intended Audience :: Developers
Classifier: Natural Language :: English
Classifier: Programming Language :: Python :: 2
Classifier: Topic :: Scientific/Engineering :: Visualization
Classifier: Topic :: Scientific/Engineering :: Chemistry
Classifier: Topic :: Scientific/Engineering :: Physics
Classifier: Topic :: Scientific/Engineering :: Medical Science Apps.
